{
  "date": "2026-05-06",
  "fetched_at": "2026-05-06T11:10:41.022Z",
  "box": {
    "id": "sv4a_box",
    "name_en": "Shiny Treasure ex Booster Box",
    "name_ja": "シャイニートレジャーex BOX",
    "snkrdunk_product_id": 151755,
    "snkrdunk_size_id": 1
  },
  "price": {
    "current_jpy": 62100,
    "previous_jpy": 20699,
    "change_jpy": 41401,
    "change_pct": 200.01,
    "direction": "up"
  },
  "sales": {
    "last_24h": 20,
    "last_7d": 20
  },
  "debug": {
    "available_sizes_in_response": [
      "3個",
      "1個",
      "5個",
      "2個",
      "4個"
    ]
  }
}