{
  "date": "2026-05-27",
  "fetched_at": "2026-05-27T04:20:16.218Z",
  "box": {
    "id": "sv4a_box",
    "name_en": "Shiny Treasure ex Booster Box",
    "name_ja": "シャイニートレジャーex BOX",
    "snkrdunk_product_id": 151755,
    "snkrdunk_size_id": 1
  },
  "price": {
    "current_jpy": 41000,
    "previous_jpy": 19000,
    "change_jpy": 22000,
    "change_pct": 115.79,
    "direction": "up"
  },
  "sales": {
    "last_24h": 7,
    "last_7d": 20
  },
  "debug": {
    "available_sizes_in_response": [
      "2個",
      "1個"
    ]
  }
}