{
  "date": "2026-06-13",
  "fetched_at": "2026-06-13T14:11:58.760Z",
  "box": {
    "id": "sv2a_box",
    "name_en": "Pokémon 151 Booster Box",
    "name_ja": "ポケモンカード151 BOX",
    "snkrdunk_product_id": 118914,
    "snkrdunk_size_id": 1
  },
  "price": {
    "current_jpy": 130000,
    "previous_jpy": 65500,
    "change_jpy": 64500,
    "change_pct": 98.47,
    "direction": "up"
  },
  "sales": {
    "last_24h": 20,
    "last_7d": 20
  },
  "debug": {
    "available_sizes_in_response": [
      "2個",
      "1個"
    ]
  }
}