{
  "date": "2026-06-10",
  "fetched_at": "2026-06-10T04:15:33.142Z",
  "box": {
    "id": "sv4a_box",
    "name_en": "Shiny Treasure ex Booster Box",
    "name_ja": "シャイニートレジャーex BOX",
    "snkrdunk_product_id": 151755,
    "snkrdunk_size_id": 1
  },
  "price": {
    "current_jpy": 179000,
    "previous_jpy": 54999,
    "change_jpy": 124001,
    "change_pct": 225.46,
    "direction": "up"
  },
  "sales": {
    "last_24h": 20,
    "last_7d": 20
  },
  "debug": {
    "available_sizes_in_response": [
      "10個",
      "1個",
      "3個",
      "20個"
    ]
  }
}