{
  "date": "2026-07-15",
  "fetched_at": "2026-07-15T10:55:28.960Z",
  "box": {
    "id": "sv4a_box",
    "name_en": "Shiny Treasure ex Booster Box",
    "name_ja": "シャイニートレジャーex BOX",
    "snkrdunk_product_id": 151755,
    "snkrdunk_size_id": 1
  },
  "price": {
    "current_jpy": 19940,
    "previous_jpy": 19000,
    "change_jpy": 940,
    "change_pct": 4.95,
    "direction": "up"
  },
  "sales": {
    "last_24h": 3,
    "last_7d": 20
  },
  "debug": {
    "available_sizes_in_response": [
      "1個",
      "2個",
      "10個"
    ]
  }
}