{
  "date": "2026-05-08",
  "fetched_at": "2026-05-08T14:03:58.692Z",
  "box": {
    "id": "sv4a_box",
    "name_en": "Shiny Treasure ex Booster Box",
    "name_ja": "シャイニートレジャーex BOX",
    "snkrdunk_product_id": 151755,
    "snkrdunk_size_id": 1
  },
  "price": {
    "current_jpy": 20500,
    "previous_jpy": 15000,
    "change_jpy": 5500,
    "change_pct": 36.67,
    "direction": "up"
  },
  "sales": {
    "last_24h": 20,
    "last_7d": 20
  },
  "debug": {
    "available_sizes_in_response": [
      "1個",
      "2個"
    ]
  }
}