{
  "date": "2026-07-01",
  "fetched_at": "2026-07-01T04:23:18.519Z",
  "box": {
    "id": "sv2a_box",
    "name_en": "Pokémon 151 Booster Box",
    "name_ja": "ポケモンカード151 BOX",
    "snkrdunk_product_id": 118914,
    "snkrdunk_size_id": 1
  },
  "price": {
    "current_jpy": 61300,
    "previous_jpy": 61400,
    "change_jpy": -100,
    "change_pct": -0.16,
    "direction": "down"
  },
  "sales": {
    "last_24h": 8,
    "last_7d": 20
  },
  "debug": {
    "available_sizes_in_response": [
      "1個",
      "2個",
      "10個",
      "4個"
    ]
  }
}